setup.py
Flask_Webhelpers.egg-info/PKG-INFO
Flask_Webhelpers.egg-info/SOURCES.txt
Flask_Webhelpers.egg-info/dependency_links.txt
Flask_Webhelpers.egg-info/not-zip-safe
Flask_Webhelpers.egg-info/requires.txt
Flask_Webhelpers.egg-info/top_level.txt
flask_webhelpers/__init__.py
flask_webhelpers/grid.py